LICENSE.txt
MANIFEST.in
setup.cfg
setup.py
yunpipe/__init__.py
yunpipe/utils.py
yunpipe.egg-info/PKG-INFO
yunpipe.egg-info/SOURCES.txt
yunpipe.egg-info/dependency_links.txt
yunpipe.egg-info/entry_points.txt
yunpipe.egg-info/not-zip-safe
yunpipe.egg-info/requires.txt
yunpipe.egg-info/top_level.txt
yunpipe/pipeline/__init__.py
yunpipe/pipeline/cleanup.py
yunpipe/pipeline/config.py
yunpipe/pipeline/image_class.py
yunpipe/pipeline/set_pipe.py
yunpipe/pipeline/task_config.py
yunpipe/scripts/__init__.py
yunpipe/scripts/setup_pipe.py
yunpipe/scripts/wrap.py
yunpipe/templates/ecs_task_definition_template.txt
yunpipe/templates/lambda_exec_role.txt
yunpipe/templates/lambda_run_task_template.txt
yunpipe/templates/runscript_template.txt
yunpipe/templates/scatter_all.txt
yunpipe/templates/ubuntu_wrapper.txt
yunpipe/wrapper/__init__.py
yunpipe/wrapper/container_wrapper.py